blobmodel/__init__.py
blobmodel/blob_shape.py
blobmodel/blobs.py
blobmodel/distributions.py
blobmodel/geometry.py
blobmodel/model.py
blobmodel/plotting.py
blobmodel/stochasticality.py
blobmodel-1.1.2.dist-info/licenses/LICENSE
blobmodel-1.1.2.dist-info/METADATA
blobmodel-1.1.2.dist-info/WHEEL
blobmodel-1.1.2.dist-info/top_level.txt
blobmodel-1.1.2.dist-info/RECORD
