Metadata-Version: 2.4
Name: blobmodel
Version: 1.1.2
Summary: Two dimensional model of propagating blobs
Author-email: gregordecristoforo <gregor.decristoforo@gmail.com>
License: MIT License
Requires-Python: >=3
License-File: LICENSE
Requires-Dist: numpy
Requires-Dist: xarray
Requires-Dist: tqdm
Requires-Dist: nptyping
Requires-Dist: matplotlib
Requires-Dist: netcdf4
Requires-Dist: pytest-cov
Requires-Dist: black
Requires-Dist: mypy
Requires-Dist: sphinx
Requires-Dist: sphinx-rtd-theme
Dynamic: license-file
